nsdcode/__init__.py
nsdcode/interp_wrapper.py
nsdcode/load_data.py
nsdcode/mapsurfacetovolume.py
nsdcode/nsd_datalocation.py
nsdcode/nsd_mapdata.py
nsdcode/nsd_output.py
nsdcode/parse_case.py
nsdcode/transform_data.py
nsdcode/utils.py
nsdcode/version.py
nsdcode/meadows/__init__.py
nsdcode/meadows/meadows.py
nsdcode/meadows/utils.py
nsdcode-1.1.dev260054000.dist-info/LICENSE
nsdcode-1.1.dev260054000.dist-info/METADATA
nsdcode-1.1.dev260054000.dist-info/WHEEL
nsdcode-1.1.dev260054000.dist-info/top_level.txt
nsdcode-1.1.dev260054000.dist-info/RECORD
