Metadata-Version: 2.1
Name: nsdcode
Version: 1.1.dev260054000
Summary: NSD map data from various spaces
Home-page: https://github.com/kendrickkay/nsdcode
Author: Ian Charest and Kendrick Kay
Author-email: charest.ian@gmail.com
Maintainer: Ian Charest
Maintainer-email: charest.ian@gmail.com
License: UNKNOWN
Platform: OS Independent
Classifier: Programming Language :: Python :: 3
Classifier: License :: OSI Approved :: MIT License
Classifier: Operating System :: OS Independent
Requires-Python: >=3.6
Requires-Dist: scikit-learn (==0.23.2)
Requires-Dist: setuptools-scm
Requires-Dist: numpy
Requires-Dist: scipy
Requires-Dist: matplotlib
Requires-Dist: nibabel (==3.1.0)
Requires-Dist: tqdm
Requires-Dist: pandas
Provides-Extra: dev
Requires-Dist: matplotlib ; extra == 'dev'
Requires-Dist: pytest ; extra == 'dev'
Requires-Dist: pytest-cov ; extra == 'dev'
Requires-Dist: pytest-benchmark ; extra == 'dev'
Requires-Dist: sphinx ; extra == 'dev'
Requires-Dist: sphinx-gallery ; extra == 'dev'
Requires-Dist: numpydoc ; extra == 'dev'
Requires-Dist: sphinx-rtd-theme ; extra == 'dev'
Requires-Dist: sphinx-copybutton ; extra == 'dev'
Requires-Dist: sphinxcontrib-matlabdomain ; extra == 'dev'
Requires-Dist: flake8 ; extra == 'dev'
